decentral_service/__init__.py
decentral_service/api.py
decentral_service/client.py
decentral_service/core.py
decentral_service/queue.py
decentral_service/storage.py
decentral_service/worker.py
examples/basic_usage.py
examples/fastapi_example/client.py
examples/fastapi_example/server.py
decentral_service-1.2.0.dist-info/METADATA
decentral_service-1.2.0.dist-info/WHEEL
decentral_service-1.2.0.dist-info/entry_points.txt
decentral_service-1.2.0.dist-info/top_level.txt
decentral_service-1.2.0.dist-info/RECORD
