Metadata-Version: 2.4
Name: decentral-service
Version: 1.2.0
Summary: A Redis-like edge microservice for multi-threaded task processing
Home-page: https://github.com/your-org/decentral-service
Author: DecentralService Team
Author-email: Manh Thang Ho <homata123@gmail.com>
License: MIT
Project-URL: Homepage, https://github.com/homata123/DecentralService
Project-URL: Repository, https://github.com/homata123/DecentralService
Project-URL: Issues, https://github.com/homata123/DecentralService/issues
Classifier: Development Status :: 4 - Beta
Classifier: Intended Audience :: Developers
Classifier: License :: OSI Approved :: MIT License
Classifier: Operating System :: OS Independent
Classifier: Programming Language :: Python :: 3
Classifier: Programming Language :: Python :: 3.8
Classifier: Programming Language :: Python :: 3.9
Classifier: Programming Language :: Python :: 3.10
Classifier: Programming Language :: Python :: 3.11
Classifier: Programming Language :: Python :: 3.12
Classifier: Topic :: Software Development :: Libraries :: Python Modules
Classifier: Topic :: System :: Distributed Computing
Classifier: Topic :: Internet :: WWW/HTTP :: HTTP Servers
Requires-Python: >=3.8
Requires-Dist: flask>=3.1.2
Requires-Dist: flask-cors>=6.0.1
Requires-Dist: psutil>=7.0.0
Requires-Dist: requests>=2.31.0
Provides-Extra: dev
Requires-Dist: pytest>=6.0; extra == "dev"
Requires-Dist: pytest-cov>=2.0; extra == "dev"
Requires-Dist: black>=21.0; extra == "dev"
Requires-Dist: flake8>=3.8; extra == "dev"
Requires-Dist: mypy>=0.800; extra == "dev"
Dynamic: author
Dynamic: home-page
Dynamic: requires-python
